aepo/Makefile
aepo/__init__.py
aepo/cli.py
aepo/make.bat
aepo/mbr/__init__.py
aepo/mbr/mbr_engine.py
aepo/mbr/policy/__init__.py
aepo/mbr/policy/diverse_mbr.py
aepo/mbr/policy/mbr.py
aepo/mbr/reward_engine.py
aepo/mbr/reward_model.py
aepo/mbr/utility_func.py
aepo/preprocess.py
aepo-0.1.6.dist-info/LICENSE
aepo-0.1.6.dist-info/METADATA
aepo-0.1.6.dist-info/WHEEL
aepo-0.1.6.dist-info/entry_points.txt
aepo-0.1.6.dist-info/RECORD
