Metadata-Version: 2.1
Name: aepo
Version: 0.1.6
Summary: Annotation Efficient Preference Optimization
Home-page: https://github.com/CyberAgentAILab/annotation-efficient-po
Author: Yuu Jinnai
Author-email: ddyuudd@gmail.com
Requires-Python: >=3.9,<4.0
Classifier: Programming Language :: Python :: 3
Classifier: Programming Language :: Python :: 3.9
Classifier: Programming Language :: Python :: 3.10
Classifier: Programming Language :: Python :: 3.11
Requires-Dist: datasets (>=2.10.0,<3.0.0)
Requires-Dist: evaluate (>=0.4.2,<0.5.0)
Requires-Dist: llm-blender (>=0.0.2,<0.0.3)
Requires-Dist: numpy (>=1.26.4,<2.0.0)
Requires-Dist: pandas (>=2.0.0,<3.0.0)
Requires-Dist: torch (>=2.3.0,<3.0.0)
Requires-Dist: tqdm (>=4.66.4,<5.0.0)
Requires-Dist: transformers (>=4.40.2,<5.0.0)
Project-URL: Documentation, https://CyberAgentAILab.github.io/annotation-efficient-po
Project-URL: Repository, https://github.com/CyberAgentAILab/annotation-efficient-po
